{
  "project_info": {
    "project_number": "527080878864",
    "project_id": "pushnotifica-c39fa",
    "storage_bucket": "pushnotifica-c39fa.appspot.com"
  },
  "client": [
    {
      "client_info": {
        "mobilesdk_app_id": "1:527080878864:android:41c72c89976d3140996b95",
        "android_client_info": {
          "package_name": "com.example.flutter_application_0"
        }
      },
      "oauth_client": [],
      "api_key": [
        {
          "current_key": "AIzaSyCsJVvtKgSQoEzgpA7yCisa1ezTltKSLK0"
        }
      ],
      "services": {
        "appinvite_service": {
          "other_platform_oauth_client": []
        }
      }
    }
  ],
  "configuration_version": "1"
}